[
        {
            "name": "Silicon Universal",
            "description": "Silicona para todos los sitios de color blanco o translucido",
            "codigo":"265968",
            "fulldescription":"Silicona para todos los sitios de color blanco o translucido",
            "img": "https://www.mundoceys.com/storage/app/media//productos/selladores/producto/sellaceys-universal-translucido-cartucho.png"
        },
        {
            "name": "Silicon Universal Numero 2",
            "description": "Silicona para todos los sitios de color blanco o translucido",
            "codigo":"265968",
            "fulldescription":"Silicona para todos los sitios de color blanco o translucido",
            "img": "https://www.mundoceys.com/storage/app/media//productos/selladores/producto/sellaceys-blanco-blister-100-ml.png"
        },
	{
            "name": "-STOP MOHO",
            "description": "STOP MOHO contrea el moho libre",
            "codigo":"265968",
            "fulldescription":"Silicona para todos los sitios de color blanco o translucido",
            "img": "https://www.mundoceys.com/storage/app/media//productos/selladores/producto/ceys-stop-moho-secado-xpress-cart-blanco.png"
        },


]